snotation/__init__.py
snotation/snotation.py
snotation-0.1.0.dist-info/METADATA
snotation-0.1.0.dist-info/WHEEL
snotation-0.1.0.dist-info/top_level.txt
snotation-0.1.0.dist-info/RECORD
