Metadata-Version: 2.2
Name: snotation
Version: 0.1.0
Summary: A lightweight scientific notation handler
Author-email: Oscar Maldonado <oscarmmgg1234@gmail.com>
Project-URL: Homepage, https://github.com/yourusername/snotation
Requires-Python: >=3.6
